crdb_schema_exporter/exporter.py
crdb_schema_exporter-0.2.1.dist-info/licenses/LICENSE
tests/test_runner.py
venv/bin/activate_this.py
crdb_schema_exporter-0.2.1.dist-info/METADATA
crdb_schema_exporter-0.2.1.dist-info/WHEEL
crdb_schema_exporter-0.2.1.dist-info/entry_points.txt
crdb_schema_exporter-0.2.1.dist-info/top_level.txt
crdb_schema_exporter-0.2.1.dist-info/RECORD
